moltbook/__init__.py
moltbook/cli.py
moltbook/client.py
moltbook-0.1.2.dist-info/licenses/LICENSE
moltbook-0.1.2.dist-info/METADATA
moltbook-0.1.2.dist-info/WHEEL
moltbook-0.1.2.dist-info/entry_points.txt
moltbook-0.1.2.dist-info/top_level.txt
moltbook-0.1.2.dist-info/RECORD
